moment/__init__.py
moment/api.py
moment/core.py
moment/date.py
moment/parse.py
moment/utils.py
moment-0.12.dist-info/METADATA
moment-0.12.dist-info/WHEEL
moment-0.12.dist-info/top_level.txt
moment-0.12.dist-info/RECORD
